mma/__init__.py
mma/mma.py
mma/MMA/__init__.py
mma/MMA/after.py
mma/MMA/alloc.py
mma/MMA/appdirs.py
mma/MMA/auto.py
mma/MMA/chords.py
mma/MMA/chordtable.py
mma/MMA/common.py
mma/MMA/debug.py
mma/MMA/docs.py
mma/MMA/exits.py
mma/MMA/file.py
mma/MMA/func.py
mma/MMA/gbl.py
mma/MMA/grooves.py
mma/MMA/harmony.py
mma/MMA/keysig.py
mma/MMA/lyric.py
mma/MMA/macro.orig.py
mma/MMA/macro.py
mma/MMA/main.py
mma/MMA/mdefine.py
mma/MMA/midi.py
mma/MMA/midiC.py
mma/MMA/midiIn.py
mma/MMA/midiM.py
mma/MMA/midifuncs.py
mma/MMA/midinote.py
mma/MMA/miditables.py
mma/MMA/notelen.py
mma/MMA/options.py
mma/MMA/ornament.py
mma/MMA/parse.py
mma/MMA/parseCL.py
mma/MMA/pat.py
mma/MMA/patAria.py
mma/MMA/patArpeggio.py
mma/MMA/patBass.py
mma/MMA/patChord.py
mma/MMA/patDrum.py
mma/MMA/patPlectrum.py
mma/MMA/patScale.py
mma/MMA/patSolo.py
mma/MMA/patWalk.py
mma/MMA/patch.py
mma/MMA/paths.py
mma/MMA/player.py
mma/MMA/pluginUtils.py
mma/MMA/rangeify.py
mma/MMA/readmidi.py
mma/MMA/regplug.py
mma/MMA/roman.py
mma/MMA/rpitch.py
mma/MMA/safe_eval.py
mma/MMA/seqrnd.py
mma/MMA/sequence.py
mma/MMA/setup.py
mma/MMA/swing.py
mma/MMA/sync.py
mma/MMA/tempo.py
mma/MMA/termsize.py
mma/MMA/timesig.py
mma/MMA/translate.py
mma/MMA/trigger.py
mma/MMA/truncate.py
mma/MMA/tweaks.py
mma/MMA/userGroove.py
mma/MMA/volume-old.py
mma/MMA/volume.py
mma/MMA/xtra.py
mma/includes/#casio-wk3000.mma#
mma/includes/README
mma/includes/casio-wk3000.mma
mma/includes/init-long.mma
mma/includes/init.mma
mma/includes/pfpats01.mma
mma/includes/reset.mma
mma/includes/roland-mt32.mma
mma/includes/stdpats.mma
mma/includes/stdpats34.mma
mma/includes/stdpats54.mma
mma/includes/stdpats68.mma
mma/lib/README
mma/lib/alexis/README
mma/lib/alexis/hiphop.mma
mma/lib/alexis/rd.py
mma/lib/alexis/teamtechno.mma
mma/lib/casio/16beat1.mma
mma/lib/casio/16beat2.mma
mma/lib/casio/16beat3.mma
mma/lib/casio/16beatballad1.mma
mma/lib/casio/16beatballad2.mma
mma/lib/casio/16beatballad3.mma
mma/lib/casio/16shuffle1.mma
mma/lib/casio/16shuffle2.mma
mma-1.5.20.2.dist-info/METADATA
mma-1.5.20.2.dist-info/WHEEL
mma-1.5.20.2.dist-info/entry_points.txt
mma-1.5.20.2.dist-info/top_level.txt
mma-1.5.20.2.dist-info/RECORD
