Metadata-Version: 2.1
Name: mma
Version: 1.5.20.2
Summary: MMA - Music Midi Accompaniment available as a pip module
Home-page: https://github.com/hugonxc/mma_pip
Author: Hugo Neves de Carvalho
Author-email: hugonvsc@gmail.com
License: UNKNOWN
Platform: UNKNOWN
Classifier: Programming Language :: Python :: 3
Classifier: Operating System :: OS Independent
Requires-Python: >=3.6
